<?xml version="1.0"?>
<!--
 /**
 * GoMage LightCheckout Extension
 *
 * @category     Extension
 * @copyright    Copyright (c) 2010-2012 GoMage (http://www.gomage.com)
 * @author       GoMage
 * @license      http://www.gomage.com/license-agreement/  Single domain license
 * @terms of use http://www.gomage.com/terms-of-use
 * @version      Release: 3.2
 */ 
 -->
<config>
    <modules>
        <GoMage_All>
            <active>true</active>
            <codePool>local</codePool>
        </GoMage_All>
	</modules>
</config>